{
  "parent": "farmersdelightexpansion:main/get_fruits",
  "criteria": {
    "eat_chorus_fruit": {
      "trigger": "minecraft:consume_item",
      "conditions": {
        "item": {
          "items": [
            "minecraft:chorus_fruit"
          ]
        }
      }
    }
  },
  "display": {
    "announce_to_chat": true,
    "description": {
      "translate": "advancements.farmersdelightexpansion.eat_chorus_fruit.desc"
    },
    "frame": "task",
    "hidden": false,
    "icon": {
      "item": "minecraft:chorus_fruit"
    },
    "show_toast": true,
    "title": {
      "translate": "advancements.farmersdelightexpansion.eat_chorus_fruit"
    }
  },
  "requirements": [
    [
      "eat_chorus_fruit"
    ]
  ],
  "sends_telemetry_event": true
}